telebaka_stickers/__init__.py
telebaka_stickers/admin.py
telebaka_stickers/bot.py
telebaka_stickers/models.py
telebaka_stickers/migrations/0001_initial.py
telebaka_stickers/migrations/__init__.py
telebaka_stickers-0.1.8.dist-info/METADATA
telebaka_stickers-0.1.8.dist-info/WHEEL
telebaka_stickers-0.1.8.dist-info/top_level.txt
telebaka_stickers-0.1.8.dist-info/RECORD
